minikai/__init__.py
minikai/api/__init__.py
minikai/api/groups/__init__.py
minikai/api/groups/add_minis_to_group.py
minikai/api/groups/add_users_to_group.py
minikai/api/groups/create_group.py
minikai/api/groups/delete_group.py
minikai/api/groups/get_group.py
minikai/api/groups/get_group_minis.py
minikai/api/groups/get_group_users.py
minikai/api/groups/get_groups.py
minikai/api/groups/get_mini_groups.py
minikai/api/groups/remove_minis_from_group.py
minikai/api/groups/remove_users_from_group.py
minikai/api/groups/update_group.py
minikai/api/minis/__init__.py
minikai/api/minis/create_mini.py
minikai/api/minis/delete_mini.py
minikai/api/minis/get_external_mini.py
minikai/api/minis/get_minis.py
minikai/api/minis/patch_mini.py
minikai/api/minis/update_mini.py
minikai/api/minis_cosmos/__init__.py
minikai/api/minis_cosmos/create_mini_cosmos.py
minikai/api/minis_cosmos/delete_mini_cosmos.py
minikai/api/minis_cosmos/delete_mini_profile_picture.py
minikai/api/minis_cosmos/get_external_mini_cosmos.py
minikai/api/minis_cosmos/get_mini_cosmos.py
minikai/api/minis_cosmos/get_mini_profile_picture.py
minikai/api/minis_cosmos/get_minis_cosmos.py
minikai/api/minis_cosmos/patch_mini_cosmos.py
minikai/api/minis_cosmos/update_mini_cosmos.py
minikai/api/minis_cosmos/upload_mini_profile_picture.py
minikai/api/minis_cosmos/upsert_external_mini_cosmos.py
minikai/api/records/__init__.py
minikai/api/records/add_attachments.py
minikai/api/records/add_relations.py
minikai/api/records/create_record.py
minikai/api/records/delete_record.py
minikai/api/records/dispose_record.py
minikai/api/records/download_attachment.py
minikai/api/records/get_created_by.py
minikai/api/records/get_labels.py
minikai/api/records/get_records.py
minikai/api/records/get_records_by_external.py
minikai/api/records/get_states.py
minikai/api/records/get_updated_by.py
minikai/api/records/remove_attachments.py
minikai/api/records/remove_relations.py
minikai/api/records/update_attachments.py
minikai-0.1.20.dist-info/WHEEL
minikai-0.1.20.dist-info/METADATA
minikai-0.1.20.dist-info/RECORD
