Metadata-Version: 2.3
Name: minikai
Version: 0.1.20
Summary: A client library for accessing Minikai Public API
Requires-Dist: httpx>=0.23.0,<0.29.0
Requires-Dist: attrs>=22.2.0
Requires-Dist: python-dateutil>=2.8.0,<3
Requires-Python: >=3.9, <4.0
